setup.py
reparse/__init__.py
reparse/builders.py
reparse/config.py
reparse/expression.py
reparse/parsers.py
reparse/util.py
reparse/validators.py
reparse.egg-info/PKG-INFO
reparse.egg-info/SOURCES.txt
reparse.egg-info/dependency_links.txt
reparse.egg-info/requires.txt
reparse.egg-info/top_level.txt