Metadata-Version: 1.1
Name: reparse
Version: 3.0
Summary: Regular Expression based parsers for extracting data from natural language
Home-page: http://github.com/andychase/reparse
Author: Andy Chase
Author-email: theandychase@gmail.com
License: MIT
Download-URL: https://github.com/andychase/reparse/archive/master.zip
Platform: UNKNOWN
Classifier: Development Status :: 5 - Production/Stable
Classifier: Intended Audience :: Developers
Classifier: Natural Language :: English
Classifier: License :: OSI Approved :: MIT License
Classifier: Programming Language :: Python
Classifier: Programming Language :: Python :: 2.7
Classifier: Programming Language :: Python :: 3.2
Classifier: Programming Language :: Python :: 3.3
Classifier: Programming Language :: Python :: 3.4
Classifier: Programming Language :: Python :: 3.5
Classifier: Topic :: Software Development :: Libraries :: Python Modules
Classifier: Topic :: Text Processing
